aithon/__init__.py
aithon/utils/__init__.py
aithon/utils/train.py
aithon-0.0.1.dist-info/LICENSE
aithon-0.0.1.dist-info/METADATA
aithon-0.0.1.dist-info/WHEEL
aithon-0.0.1.dist-info/top_level.txt
aithon-0.0.1.dist-info/RECORD
