Metadata-Version: 2.1
Name: aithon
Version: 0.0.1
Summary: Aithon is a library for use in AI hackathon.
Home-page: https://github.com/baek2sm/aithon
Author: SeungBaek Hong
Author-email: baek2sm@gmail.com
License: MIT
Platform: UNKNOWN
Classifier: License :: OSI Approved :: MIT License
Classifier: Operating System :: OS Independent
Classifier: Programming Language :: Python :: 3.9
License-File: LICENSE
